{
    "historico_periodos": [
        {
            "fondos": [
                {
                    "cantidad": 168935.0,
                    "desde": "2014T1",
                    "isin": "ES0180792006",
                    "nombre": "TRUE VALUE, FI",
                    "porcentaje": 3.75
                }
            ],
            "periodo": "2014T4"
        },
        {
            "fondos": [
                {
                    "cantidad": 78207.0,
                    "desde": "2014T1",
                    "isin": "ES0180792006",
                    "nombre": "TRUE VALUE, FI",
                    "porcentaje": 2.31
                }
            ],
            "periodo": "2014T3"
        },
        {
            "fondos": [
                {
                    "cantidad": 94586.0,
                    "desde": "2014T1",
                    "isin": "ES0180792006",
                    "nombre": "TRUE VALUE, FI",
                    "porcentaje": 2.98
                }
            ],
            "periodo": "2014T2"
        },
        {
            "fondos": [
                {
                    "cantidad": 92358.0,
                    "desde": "2014T1",
                    "isin": "ES0180792006",
                    "nombre": "TRUE VALUE, FI",
                    "porcentaje": 3.33
                }
            ],
            "periodo": "2014T1"
        }
    ],
    "isin": "BMG2110R1144",
    "nombre": "ACCIONES|CHIPMOS TECHNOLOGIES BERMUDA"
}