{
    "historico_periodos": [
        {
            "fondos": [
                {
                    "cantidad": 17568662.0,
                    "desde": "2016T3",
                    "isin": "ES0164735039",
                    "nombre": "LABORAL KUTXA AVANT,FI",
                    "porcentaje": 4.31
                }
            ],
            "periodo": "2019T4"
        },
        {
            "fondos": [
                {
                    "cantidad": 16554998.0,
                    "desde": "2016T3",
                    "isin": "ES0164735039",
                    "nombre": "LABORAL KUTXA AVANT,FI",
                    "porcentaje": 4.44
                }
            ],
            "periodo": "2019T3"
        },
        {
            "fondos": [
                {
                    "cantidad": 16012447.0,
                    "desde": "2016T3",
                    "isin": "ES0164735039",
                    "nombre": "LABORAL KUTXA AVANT,FI",
                    "porcentaje": 4.43
                }
            ],
            "periodo": "2019T2"
        },
        {
            "fondos": [
                {
                    "cantidad": 15350927.0,
                    "desde": "2016T3",
                    "isin": "ES0164735039",
                    "nombre": "LABORAL KUTXA AVANT,FI",
                    "porcentaje": 4.45
                }
            ],
            "periodo": "2019T1"
        },
        {
            "fondos": [
                {
                    "cantidad": 14636780.0,
                    "desde": "2016T3",
                    "isin": "ES0164735039",
                    "nombre": "LABORAL KUTXA AVANT,FI",
                    "porcentaje": 4.54
                }
            ],
            "periodo": "2018T4"
        },
        {
            "fondos": [
                {
                    "cantidad": 14283781.0,
                    "desde": "2016T3",
                    "isin": "ES0164735039",
                    "nombre": "LABORAL KUTXA AVANT,FI",
                    "porcentaje": 4.43
                }
            ],
            "periodo": "2018T3"
        },
        {
            "fondos": [
                {
                    "cantidad": 13908160.0,
                    "desde": "2016T3",
                    "isin": "ES0164735039",
                    "nombre": "LABORAL KUTXA AVANT,FI",
                    "porcentaje": 4.46
                }
            ],
            "periodo": "2018T2"
        },
        {
            "fondos": [
                {
                    "cantidad": 13354472.0,
                    "desde": "2016T3",
                    "isin": "ES0164735039",
                    "nombre": "LABORAL KUTXA AVANT,FI",
                    "porcentaje": 4.5
                }
            ],
            "periodo": "2018T1"
        },
        {
            "fondos": [
                {
                    "cantidad": 11439458.0,
                    "desde": "2016T3",
                    "isin": "ES0164735039",
                    "nombre": "LABORAL KUTXA AVANT,FI",
                    "porcentaje": 4.47
                }
            ],
            "periodo": "2017T4"
        },
        {
            "fondos": [
                {
                    "cantidad": 8716351.0,
                    "desde": "2016T3",
                    "isin": "ES0164735039",
                    "nombre": "LABORAL KUTXA AVANT,FI",
                    "porcentaje": 4.48
                }
            ],
            "periodo": "2017T3"
        },
        {
            "fondos": [
                {
                    "cantidad": 6223607.0,
                    "desde": "2016T3",
                    "isin": "ES0164735039",
                    "nombre": "LABORAL KUTXA AVANT,FI",
                    "porcentaje": 4.31
                }
            ],
            "periodo": "2017T2"
        },
        {
            "fondos": [
                {
                    "cantidad": 4504105.0,
                    "desde": "2016T3",
                    "isin": "ES0164735039",
                    "nombre": "LABORAL KUTXA AVANT,FI",
                    "porcentaje": 4.25
                }
            ],
            "periodo": "2017T1"
        },
        {
            "fondos": [
                {
                    "cantidad": 3442868.0,
                    "desde": "2016T3",
                    "isin": "ES0164735039",
                    "nombre": "LABORAL KUTXA AVANT,FI",
                    "porcentaje": 4.87
                }
            ],
            "periodo": "2016T4"
        },
        {
            "fondos": [
                {
                    "cantidad": 1472043.0,
                    "desde": "2016T3",
                    "isin": "ES0164735039",
                    "nombre": "LABORAL KUTXA AVANT,FI",
                    "porcentaje": 4.39
                }
            ],
            "periodo": "2016T3"
        }
    ],
    "isin": "IE00B3D1YW09",
    "nombre": "PARTICIPACIONES|PIMCO CAPITAL SEC"
}