{
    "historico_periodos": [
        {
            "fondos": [
                {
                    "cantidad": 0.0,
                    "desde": "2019T4",
                    "isin": "ES0126551003",
                    "nombre": "GESTIFONSA RENTA FIJA CORTO PLAZO, FI CLASE CARTERA",
                    "porcentaje": 0.0
                },
                {
                    "cantidad": 0.0,
                    "desde": "2019T4",
                    "isin": "ES0126551037",
                    "nombre": "GESTIFONSA RENTA FIJA CORTO PLAZO, FI CLASE BASE",
                    "porcentaje": 0.0
                },
                {
                    "cantidad": 0.0,
                    "desde": "2020T2",
                    "isin": "ES0138712007",
                    "nombre": "GESTIFONSA RENTA FIJA EURO, FI CLASE CARTERA",
                    "porcentaje": 0.0
                },
                {
                    "cantidad": 0.0,
                    "desde": "2020T2",
                    "isin": "ES0138712031",
                    "nombre": "GESTIFONSA RENTA FIJA EURO, FI CLASE BASE",
                    "porcentaje": 0.0
                },
                {
                    "cantidad": 0.0,
                    "desde": "2020T4",
                    "isin": "ES0181073034",
                    "nombre": "UNIFOND FUSIÓN RENTA FIJA EURO, FI",
                    "porcentaje": 0.0
                },
                {
                    "cantidad": 0.0,
                    "desde": "2020T4",
                    "isin": "ES0181074008",
                    "nombre": "UNIFOND RENTA FIJA EURO, FI CLASE C",
                    "porcentaje": 0.0
                },
                {
                    "cantidad": 0.0,
                    "desde": "2020T4",
                    "isin": "ES0181074016",
                    "nombre": "UNIFOND RENTA FIJA EURO, FI CLASE F",
                    "porcentaje": 0.0
                },
                {
                    "cantidad": 0.0,
                    "desde": "2020T4",
                    "isin": "ES0181074032",
                    "nombre": "UNIFOND RENTA FIJA EURO, FI CLASE A",
                    "porcentaje": 0.0
                }
            ],
            "periodo": "2021T2"
        },
        {
            "fondos": [
                {
                    "cantidad": 5249102.0,
                    "desde": "2020T4",
                    "isin": "ES0170156006",
                    "nombre": "SANTALUCIA RENTA FIJA CORTO PLAZO EURO, FI CLASE A",
                    "porcentaje": 2.24
                },
                {
                    "cantidad": 5249102.0,
                    "desde": "2020T4",
                    "isin": "ES0170156022",
                    "nombre": "SANTALUCIA RENTA FIJA CORTO PLAZO EURO, FI CLASE C",
                    "porcentaje": 2.24
                },
                {
                    "cantidad": 5249102.0,
                    "desde": "2020T4",
                    "isin": "ES0170156030",
                    "nombre": "SANTALUCIA RENTA FIJA CORTO PLAZO EURO, FI CLASE B",
                    "porcentaje": 2.24
                },
                {
                    "cantidad": 606038.0,
                    "desde": "2019T4",
                    "isin": "ES0126551003",
                    "nombre": "GESTIFONSA RENTA FIJA CORTO PLAZO, FI CLASE CARTERA",
                    "porcentaje": 1.2
                },
                {
                    "cantidad": 606038.0,
                    "desde": "2019T4",
                    "isin": "ES0126551037",
                    "nombre": "GESTIFONSA RENTA FIJA CORTO PLAZO, FI CLASE BASE",
                    "porcentaje": 1.2
                },
                {
                    "cantidad": 6935623.0,
                    "desde": "2020T2",
                    "isin": "ES0119483008",
                    "nombre": "ABANCA RENTA FIJA PATRIMONIO, FI CLASE A",
                    "porcentaje": 1.08
                },
                {
                    "cantidad": 978326.0,
                    "desde": "2018T1",
                    "isin": "ES0138816006",
                    "nombre": "MEDIOLANUM FONDCUENTA, FI CLASE E",
                    "porcentaje": 0.93
                },
                {
                    "cantidad": 978326.0,
                    "desde": "2018T1",
                    "isin": "ES0138816030",
                    "nombre": "MEDIOLANUM FONDCUENTA, FI CLASE S",
                    "porcentaje": 0.93
                },
                {
                    "cantidad": 1028387.0,
                    "desde": "2020T3",
                    "isin": "ES0107432009",
                    "nombre": "IMANTIA RENTA FIJA DURACION 0-2, FI INSTITUCIONAL",
                    "porcentaje": 0.7
                },
                {
                    "cantidad": 1028387.0,
                    "desde": "2020T3",
                    "isin": "ES0107432033",
                    "nombre": "IMANTIA RENTA FIJA DURACION 0-2, FI MINORISTA",
                    "porcentaje": 0.7
                },
                {
                    "cantidad": 3232639.0,
                    "desde": "2020T4",
                    "isin": "ES0181074008",
                    "nombre": "UNIFOND RENTA FIJA EURO, FI CLASE C",
                    "porcentaje": 0.64
                },
                {
                    "cantidad": 3232639.0,
                    "desde": "2020T4",
                    "isin": "ES0181074016",
                    "nombre": "UNIFOND RENTA FIJA EURO, FI CLASE F",
                    "porcentaje": 0.64
                },
                {
                    "cantidad": 3232639.0,
                    "desde": "2020T4",
                    "isin": "ES0181074032",
                    "nombre": "UNIFOND RENTA FIJA EURO, FI CLASE A",
                    "porcentaje": 0.64
                },
                {
                    "cantidad": 303060.0,
                    "desde": "2020T4",
                    "isin": "ES0181073034",
                    "nombre": "UNIFOND FUSIÓN RENTA FIJA EURO, FI",
                    "porcentaje": 0.55
                },
                {
                    "cantidad": 214297.0,
                    "desde": "2019T3",
                    "isin": "ES0137389005",
                    "nombre": "MEDIOLANUM CRECIMIENTO, FI CLASE L-A",
                    "porcentaje": 0.54
                },
                {
                    "cantidad": 214297.0,
                    "desde": "2019T3",
                    "isin": "ES0137389013",
                    "nombre": "MEDIOLANUM CRECIMIENTO, FI CLASE L-B",
                    "porcentaje": 0.54
                },
                {
                    "cantidad": 214297.0,
                    "desde": "2019T3",
                    "isin": "ES0137389021",
                    "nombre": "MEDIOLANUM CRECIMIENTO, FI CLASE S-B",
                    "porcentaje": 0.54
                },
                {
                    "cantidad": 214297.0,
                    "desde": "2019T3",
                    "isin": "ES0137389039",
                    "nombre": "MEDIOLANUM CRECIMIENTO, FI CLASE S-A",
                    "porcentaje": 0.54
                },
                {
                    "cantidad": 214297.0,
                    "desde": "2019T3",
                    "isin": "ES0137389047",
                    "nombre": "MEDIOLANUM CRECIMIENTO, FI CLASE E-A",
                    "porcentaje": 0.54
                },
                {
                    "cantidad": 214297.0,
                    "desde": "2019T3",
                    "isin": "ES0137389054",
                    "nombre": "MEDIOLANUM CRECIMIENTO, FI CLASE E-B",
                    "porcentaje": 0.54
                },
                {
                    "cantidad": 404025.0,
                    "desde": "2020T2",
                    "isin": "ES0138712007",
                    "nombre": "GESTIFONSA RENTA FIJA EURO, FI CLASE CARTERA",
                    "porcentaje": 0.49
                },
                {
                    "cantidad": 404025.0,
                    "desde": "2020T2",
                    "isin": "ES0138712031",
                    "nombre": "GESTIFONSA RENTA FIJA EURO, FI CLASE BASE",
                    "porcentaje": 0.49
                },
                {
                    "cantidad": 107123.0,
                    "desde": "2019T3",
                    "isin": "ES0180552004",
                    "nombre": "TREA CAJAMAR VALOR, FI",
                    "porcentaje": 0.4
                },
                {
                    "cantidad": 856979.0,
                    "desde": "2019T3",
                    "isin": "ES0114547039",
                    "nombre": "TREA CAJAMAR PATRIMONIO FI",
                    "porcentaje": 0.21
                },
                {
                    "cantidad": 214244.0,
                    "desde": "2019T3",
                    "isin": "ES0109226037",
                    "nombre": "TREA CAJAMAR CRECIMIENTO FI",
                    "porcentaje": 0.2
                },
                {
                    "cantidad": 1062980.0,
                    "desde": "2020T4",
                    "isin": "ES0114546007",
                    "nombre": "TREA CAJAMAR CORTO PLAZO FI CLASE B",
                    "porcentaje": 0.18
                },
                {
                    "cantidad": 1062980.0,
                    "desde": "2019T4",
                    "isin": "ES0114546031",
                    "nombre": "TREA CAJAMAR CORTO PLAZO FI CLASE A",
                    "porcentaje": 0.18
                },
                {
                    "cantidad": 1350990.0,
                    "desde": "2017T3",
                    "isin": "ES0165127004",
                    "nombre": "MEDIOLANUM ACTIVO, FI CLASE L-A",
                    "porcentaje": 0.13
                },
                {
                    "cantidad": 1350990.0,
                    "desde": "2017T3",
                    "isin": "ES0165127012",
                    "nombre": "MEDIOLANUM ACTIVO, FI CLASE S-B",
                    "porcentaje": 0.13
                },
                {
                    "cantidad": 1350990.0,
                    "desde": "2017T3",
                    "isin": "ES0165127020",
                    "nombre": "MEDIOLANUM ACTIVO, FI CLASE L-B",
                    "porcentaje": 0.13
                },
                {
                    "cantidad": 1350990.0,
                    "desde": "2017T3",
                    "isin": "ES0165127038",
                    "nombre": "MEDIOLANUM ACTIVO, FI CLASE S-A",
                    "porcentaje": 0.13
                },
                {
                    "cantidad": 1350990.0,
                    "desde": "2017T3",
                    "isin": "ES0165127046",
                    "nombre": "MEDIOLANUM ACTIVO, FI CLASE E-A",
                    "porcentaje": 0.13
                },
                {
                    "cantidad": 1350990.0,
                    "desde": "2017T3",
                    "isin": "ES0165127053",
                    "nombre": "MEDIOLANUM ACTIVO, FI CLASE E-B",
                    "porcentaje": 0.13
                }
            ],
            "periodo": "2021T1"
        },
        {
            "fondos": [
                {
                    "cantidad": 2746085.0,
                    "desde": "2020T4",
                    "isin": "ES0170156006",
                    "nombre": "SANTALUCIA RENTA FIJA CORTO PLAZO EURO, FI CLASE A",
                    "porcentaje": 1.19
                },
                {
                    "cantidad": 2746085.0,
                    "desde": "2020T4",
                    "isin": "ES0170156022",
                    "nombre": "SANTALUCIA RENTA FIJA CORTO PLAZO EURO, FI CLASE C",
                    "porcentaje": 1.19
                },
                {
                    "cantidad": 2746085.0,
                    "desde": "2020T4",
                    "isin": "ES0170156030",
                    "nombre": "SANTALUCIA RENTA FIJA CORTO PLAZO EURO, FI CLASE B",
                    "porcentaje": 1.19
                },
                {
                    "cantidad": 612111.0,
                    "desde": "2019T4",
                    "isin": "ES0126551003",
                    "nombre": "GESTIFONSA RENTA FIJA CORTO PLAZO, FI CLASE CARTERA",
                    "porcentaje": 1.11
                },
                {
                    "cantidad": 612111.0,
                    "desde": "2019T4",
                    "isin": "ES0126551037",
                    "nombre": "GESTIFONSA RENTA FIJA CORTO PLAZO, FI CLASE BASE",
                    "porcentaje": 1.11
                },
                {
                    "cantidad": 981738.0,
                    "desde": "2018T1",
                    "isin": "ES0138816006",
                    "nombre": "MEDIOLANUM FONDCUENTA, FI CLASE E",
                    "porcentaje": 0.97
                },
                {
                    "cantidad": 981738.0,
                    "desde": "2018T1",
                    "isin": "ES0138816030",
                    "nombre": "MEDIOLANUM FONDCUENTA, FI CLASE S",
                    "porcentaje": 0.97
                },
                {
                    "cantidad": 6042488.0,
                    "desde": "2020T2",
                    "isin": "ES0119483008",
                    "nombre": "ABANCA RENTA FIJA PATRIMONIO, FI CLASE A",
                    "porcentaje": 0.91
                },
                {
                    "cantidad": 1030677.0,
                    "desde": "2020T3",
                    "isin": "ES0107432009",
                    "nombre": "IMANTIA RENTA FIJA DURACION 0-2, FI INSTITUCIONAL",
                    "porcentaje": 0.63
                },
                {
                    "cantidad": 1030677.0,
                    "desde": "2020T3",
                    "isin": "ES0107432033",
                    "nombre": "IMANTIA RENTA FIJA DURACION 0-2, FI MINORISTA",
                    "porcentaje": 0.63
                },
                {
                    "cantidad": 3265015.0,
                    "desde": "2020T4",
                    "isin": "ES0181074008",
                    "nombre": "UNIFOND RENTA FIJA EURO, FI CLASE C",
                    "porcentaje": 0.62
                },
                {
                    "cantidad": 3265015.0,
                    "desde": "2020T4",
                    "isin": "ES0181074016",
                    "nombre": "UNIFOND RENTA FIJA EURO, FI CLASE F",
                    "porcentaje": 0.62
                },
                {
                    "cantidad": 3265015.0,
                    "desde": "2020T4",
                    "isin": "ES0181074032",
                    "nombre": "UNIFOND RENTA FIJA EURO, FI CLASE A",
                    "porcentaje": 0.62
                },
                {
                    "cantidad": 306096.0,
                    "desde": "2020T4",
                    "isin": "ES0181073034",
                    "nombre": "UNIFOND FUSIÓN RENTA FIJA EURO, FI",
                    "porcentaje": 0.53
                },
                {
                    "cantidad": 214449.0,
                    "desde": "2019T3",
                    "isin": "ES0137389005",
                    "nombre": "MEDIOLANUM CRECIMIENTO, FI CLASE L-A",
                    "porcentaje": 0.47
                },
                {
                    "cantidad": 214449.0,
                    "desde": "2019T3",
                    "isin": "ES0137389013",
                    "nombre": "MEDIOLANUM CRECIMIENTO, FI CLASE L-B",
                    "porcentaje": 0.47
                },
                {
                    "cantidad": 214449.0,
                    "desde": "2019T3",
                    "isin": "ES0137389021",
                    "nombre": "MEDIOLANUM CRECIMIENTO, FI CLASE S-B",
                    "porcentaje": 0.47
                },
                {
                    "cantidad": 214449.0,
                    "desde": "2019T3",
                    "isin": "ES0137389039",
                    "nombre": "MEDIOLANUM CRECIMIENTO, FI CLASE S-A",
                    "porcentaje": 0.47
                },
                {
                    "cantidad": 214449.0,
                    "desde": "2019T3",
                    "isin": "ES0137389047",
                    "nombre": "MEDIOLANUM CRECIMIENTO, FI CLASE E-A",
                    "porcentaje": 0.47
                },
                {
                    "cantidad": 214449.0,
                    "desde": "2019T3",
                    "isin": "ES0137389054",
                    "nombre": "MEDIOLANUM CRECIMIENTO, FI CLASE E-B",
                    "porcentaje": 0.47
                },
                {
                    "cantidad": 408074.0,
                    "desde": "2020T2",
                    "isin": "ES0138712007",
                    "nombre": "GESTIFONSA RENTA FIJA EURO, FI CLASE CARTERA",
                    "porcentaje": 0.46
                },
                {
                    "cantidad": 408074.0,
                    "desde": "2020T2",
                    "isin": "ES0138712031",
                    "nombre": "GESTIFONSA RENTA FIJA EURO, FI CLASE BASE",
                    "porcentaje": 0.46
                },
                {
                    "cantidad": 107131.0,
                    "desde": "2019T3",
                    "isin": "ES0180552004",
                    "nombre": "TREA CAJAMAR VALOR, FI",
                    "porcentaje": 0.39
                },
                {
                    "cantidad": 857040.0,
                    "desde": "2019T3",
                    "isin": "ES0114547039",
                    "nombre": "TREA CAJAMAR PATRIMONIO FI",
                    "porcentaje": 0.21
                },
                {
                    "cantidad": 214259.0,
                    "desde": "2019T3",
                    "isin": "ES0109226037",
                    "nombre": "TREA CAJAMAR CRECIMIENTO FI",
                    "porcentaje": 0.19
                },
                {
                    "cantidad": 1062477.0,
                    "desde": "2020T4",
                    "isin": "ES0114546007",
                    "nombre": "TREA CAJAMAR CORTO PLAZO FI CLASE B",
                    "porcentaje": 0.19
                },
                {
                    "cantidad": 1062477.0,
                    "desde": "2019T4",
                    "isin": "ES0114546031",
                    "nombre": "TREA CAJAMAR CORTO PLAZO FI CLASE A",
                    "porcentaje": 0.19
                },
                {
                    "cantidad": 1353671.0,
                    "desde": "2017T3",
                    "isin": "ES0165127004",
                    "nombre": "MEDIOLANUM ACTIVO, FI CLASE L-A",
                    "porcentaje": 0.15
                },
                {
                    "cantidad": 1353671.0,
                    "desde": "2017T3",
                    "isin": "ES0165127012",
                    "nombre": "MEDIOLANUM ACTIVO, FI CLASE S-B",
                    "porcentaje": 0.15
                },
                {
                    "cantidad": 1353671.0,
                    "desde": "2017T3",
                    "isin": "ES0165127020",
                    "nombre": "MEDIOLANUM ACTIVO, FI CLASE L-B",
                    "porcentaje": 0.15
                },
                {
                    "cantidad": 1353671.0,
                    "desde": "2017T3",
                    "isin": "ES0165127038",
                    "nombre": "MEDIOLANUM ACTIVO, FI CLASE S-A",
                    "porcentaje": 0.15
                },
                {
                    "cantidad": 1353671.0,
                    "desde": "2017T3",
                    "isin": "ES0165127046",
                    "nombre": "MEDIOLANUM ACTIVO, FI CLASE E-A",
                    "porcentaje": 0.15
                },
                {
                    "cantidad": 1353671.0,
                    "desde": "2017T3",
                    "isin": "ES0165127053",
                    "nombre": "MEDIOLANUM ACTIVO, FI CLASE E-B",
                    "porcentaje": 0.15
                }
            ],
            "periodo": "2020T4"
        },
        {
            "fondos": [
                {
                    "cantidad": 981370.0,
                    "desde": "2018T1",
                    "isin": "ES0138816006",
                    "nombre": "MEDIOLANUM FONDCUENTA, FI CLASE E",
                    "porcentaje": 0.97
                },
                {
                    "cantidad": 981370.0,
                    "desde": "2018T1",
                    "isin": "ES0138816030",
                    "nombre": "MEDIOLANUM FONDCUENTA, FI CLASE S",
                    "porcentaje": 0.97
                },
                {
                    "cantidad": 6033964.0,
                    "desde": "2020T2",
                    "isin": "ES0119483008",
                    "nombre": "ABANCA RENTA FIJA PATRIMONIO, FI CLASE A",
                    "porcentaje": 0.93
                },
                {
                    "cantidad": 618378.0,
                    "desde": "2019T4",
                    "isin": "ES0126551003",
                    "nombre": "GESTIFONSA RENTA FIJA CORTO PLAZO, FI CLASE CARTERA",
                    "porcentaje": 0.88
                },
                {
                    "cantidad": 618378.0,
                    "desde": "2019T4",
                    "isin": "ES0126551037",
                    "nombre": "GESTIFONSA RENTA FIJA CORTO PLAZO, FI CLASE BASE",
                    "porcentaje": 0.88
                },
                {
                    "cantidad": 1028864.0,
                    "desde": "2020T3",
                    "isin": "ES0107432009",
                    "nombre": "IMANTIA RENTA FIJA DURACION 0-2, FI INSTITUCIONAL",
                    "porcentaje": 0.63
                },
                {
                    "cantidad": 1028864.0,
                    "desde": "2020T3",
                    "isin": "ES0107432033",
                    "nombre": "IMANTIA RENTA FIJA DURACION 0-2, FI MINORISTA",
                    "porcentaje": 0.63
                },
                {
                    "cantidad": 412252.0,
                    "desde": "2020T2",
                    "isin": "ES0138712007",
                    "nombre": "GESTIFONSA RENTA FIJA EURO, FI CLASE CARTERA",
                    "porcentaje": 0.47
                },
                {
                    "cantidad": 412252.0,
                    "desde": "2020T2",
                    "isin": "ES0138712031",
                    "nombre": "GESTIFONSA RENTA FIJA EURO, FI CLASE BASE",
                    "porcentaje": 0.47
                },
                {
                    "cantidad": 213744.0,
                    "desde": "2019T3",
                    "isin": "ES0137389005",
                    "nombre": "MEDIOLANUM CRECIMIENTO, FI CLASE L-A",
                    "porcentaje": 0.46
                },
                {
                    "cantidad": 213744.0,
                    "desde": "2019T3",
                    "isin": "ES0137389013",
                    "nombre": "MEDIOLANUM CRECIMIENTO, FI CLASE L-B",
                    "porcentaje": 0.46
                },
                {
                    "cantidad": 213744.0,
                    "desde": "2019T3",
                    "isin": "ES0137389021",
                    "nombre": "MEDIOLANUM CRECIMIENTO, FI CLASE S-B",
                    "porcentaje": 0.46
                },
                {
                    "cantidad": 213744.0,
                    "desde": "2019T3",
                    "isin": "ES0137389039",
                    "nombre": "MEDIOLANUM CRECIMIENTO, FI CLASE S-A",
                    "porcentaje": 0.46
                },
                {
                    "cantidad": 213744.0,
                    "desde": "2019T3",
                    "isin": "ES0137389047",
                    "nombre": "MEDIOLANUM CRECIMIENTO, FI CLASE E-A",
                    "porcentaje": 0.46
                },
                {
                    "cantidad": 213744.0,
                    "desde": "2019T3",
                    "isin": "ES0137389054",
                    "nombre": "MEDIOLANUM CRECIMIENTO, FI CLASE E-B",
                    "porcentaje": 0.46
                },
                {
                    "cantidad": 107418.0,
                    "desde": "2019T3",
                    "isin": "ES0180552004",
                    "nombre": "TREA CAJAMAR VALOR, FI",
                    "porcentaje": 0.38
                },
                {
                    "cantidad": 859334.0,
                    "desde": "2019T3",
                    "isin": "ES0114547039",
                    "nombre": "TREA CAJAMAR PATRIMONIO FI",
                    "porcentaje": 0.2
                },
                {
                    "cantidad": 214833.0,
                    "desde": "2019T3",
                    "isin": "ES0109226037",
                    "nombre": "TREA CAJAMAR CRECIMIENTO FI",
                    "porcentaje": 0.19
                },
                {
                    "cantidad": 1064756.0,
                    "desde": "2019T4",
                    "isin": "ES0114546031",
                    "nombre": "TREA CAJAMAR CORTO PLAZO FI CLASE A",
                    "porcentaje": 0.19
                },
                {
                    "cantidad": 1351049.0,
                    "desde": "2017T3",
                    "isin": "ES0165127004",
                    "nombre": "MEDIOLANUM ACTIVO, FI CLASE L-A",
                    "porcentaje": 0.17
                },
                {
                    "cantidad": 1351049.0,
                    "desde": "2017T3",
                    "isin": "ES0165127012",
                    "nombre": "MEDIOLANUM ACTIVO, FI CLASE S-B",
                    "porcentaje": 0.17
                },
                {
                    "cantidad": 1351049.0,
                    "desde": "2017T3",
                    "isin": "ES0165127020",
                    "nombre": "MEDIOLANUM ACTIVO, FI CLASE L-B",
                    "porcentaje": 0.17
                },
                {
                    "cantidad": 1351049.0,
                    "desde": "2017T3",
                    "isin": "ES0165127038",
                    "nombre": "MEDIOLANUM ACTIVO, FI CLASE S-A",
                    "porcentaje": 0.17
                },
                {
                    "cantidad": 1351049.0,
                    "desde": "2017T3",
                    "isin": "ES0165127046",
                    "nombre": "MEDIOLANUM ACTIVO, FI CLASE E-A",
                    "porcentaje": 0.17
                },
                {
                    "cantidad": 1351049.0,
                    "desde": "2017T3",
                    "isin": "ES0165127053",
                    "nombre": "MEDIOLANUM ACTIVO, FI CLASE E-B",
                    "porcentaje": 0.17
                }
            ],
            "periodo": "2020T3"
        },
        {
            "fondos": [
                {
                    "cantidad": 617851.0,
                    "desde": "2019T4",
                    "isin": "ES0126551003",
                    "nombre": "GESTIFONSA RENTA FIJA CORTO PLAZO, FI CLASE CARTERA",
                    "porcentaje": 1.12
                },
                {
                    "cantidad": 617851.0,
                    "desde": "2019T4",
                    "isin": "ES0126551037",
                    "nombre": "GESTIFONSA RENTA FIJA CORTO PLAZO, FI CLASE BASE",
                    "porcentaje": 1.12
                },
                {
                    "cantidad": 978889.0,
                    "desde": "2018T1",
                    "isin": "ES0138816006",
                    "nombre": "MEDIOLANUM FONDCUENTA, FI CLASE E",
                    "porcentaje": 0.96
                },
                {
                    "cantidad": 978889.0,
                    "desde": "2018T1",
                    "isin": "ES0138816030",
                    "nombre": "MEDIOLANUM FONDCUENTA, FI CLASE S",
                    "porcentaje": 0.96
                },
                {
                    "cantidad": 411900.0,
                    "desde": "2020T2",
                    "isin": "ES0138712007",
                    "nombre": "GESTIFONSA RENTA FIJA EURO, FI CLASE CARTERA",
                    "porcentaje": 0.47
                },
                {
                    "cantidad": 411900.0,
                    "desde": "2020T2",
                    "isin": "ES0138712031",
                    "nombre": "GESTIFONSA RENTA FIJA EURO, FI CLASE BASE",
                    "porcentaje": 0.47
                },
                {
                    "cantidad": 212566.0,
                    "desde": "2019T3",
                    "isin": "ES0137389005",
                    "nombre": "MEDIOLANUM CRECIMIENTO, FI CLASE L-A",
                    "porcentaje": 0.44
                },
                {
                    "cantidad": 212566.0,
                    "desde": "2019T3",
                    "isin": "ES0137389013",
                    "nombre": "MEDIOLANUM CRECIMIENTO, FI CLASE L-B",
                    "porcentaje": 0.44
                },
                {
                    "cantidad": 212566.0,
                    "desde": "2019T3",
                    "isin": "ES0137389021",
                    "nombre": "MEDIOLANUM CRECIMIENTO, FI CLASE S-B",
                    "porcentaje": 0.44
                },
                {
                    "cantidad": 212566.0,
                    "desde": "2019T3",
                    "isin": "ES0137389039",
                    "nombre": "MEDIOLANUM CRECIMIENTO, FI CLASE S-A",
                    "porcentaje": 0.44
                },
                {
                    "cantidad": 212566.0,
                    "desde": "2019T3",
                    "isin": "ES0137389047",
                    "nombre": "MEDIOLANUM CRECIMIENTO, FI CLASE E-A",
                    "porcentaje": 0.44
                },
                {
                    "cantidad": 212566.0,
                    "desde": "2019T3",
                    "isin": "ES0137389054",
                    "nombre": "MEDIOLANUM CRECIMIENTO, FI CLASE E-B",
                    "porcentaje": 0.44
                },
                {
                    "cantidad": 106099.0,
                    "desde": "2019T3",
                    "isin": "ES0180552004",
                    "nombre": "TREA CAJAMAR VALOR, FI",
                    "porcentaje": 0.36
                },
                {
                    "cantidad": 1050968.0,
                    "desde": "2019T4",
                    "isin": "ES0114546031",
                    "nombre": "TREA CAJAMAR CORTO PLAZO FI CLASE A",
                    "porcentaje": 0.19
                },
                {
                    "cantidad": 848780.0,
                    "desde": "2019T3",
                    "isin": "ES0114547039",
                    "nombre": "TREA CAJAMAR PATRIMONIO FI",
                    "porcentaje": 0.19
                },
                {
                    "cantidad": 212195.0,
                    "desde": "2019T3",
                    "isin": "ES0109226037",
                    "nombre": "TREA CAJAMAR CRECIMIENTO FI",
                    "porcentaje": 0.18
                },
                {
                    "cantidad": 1345480.0,
                    "desde": "2017T3",
                    "isin": "ES0165127004",
                    "nombre": "MEDIOLANUM ACTIVO, FI CLASE L-A",
                    "porcentaje": 0.18
                },
                {
                    "cantidad": 1345480.0,
                    "desde": "2017T3",
                    "isin": "ES0165127012",
                    "nombre": "MEDIOLANUM ACTIVO, FI CLASE S-B",
                    "porcentaje": 0.18
                },
                {
                    "cantidad": 1345480.0,
                    "desde": "2017T3",
                    "isin": "ES0165127020",
                    "nombre": "MEDIOLANUM ACTIVO, FI CLASE L-B",
                    "porcentaje": 0.18
                },
                {
                    "cantidad": 1345480.0,
                    "desde": "2017T3",
                    "isin": "ES0165127038",
                    "nombre": "MEDIOLANUM ACTIVO, FI CLASE S-A",
                    "porcentaje": 0.18
                },
                {
                    "cantidad": 1345480.0,
                    "desde": "2017T3",
                    "isin": "ES0165127046",
                    "nombre": "MEDIOLANUM ACTIVO, FI CLASE E-A",
                    "porcentaje": 0.18
                },
                {
                    "cantidad": 1345480.0,
                    "desde": "2017T3",
                    "isin": "ES0165127053",
                    "nombre": "MEDIOLANUM ACTIVO, FI CLASE E-B",
                    "porcentaje": 0.18
                },
                {
                    "cantidad": 1030034.0,
                    "desde": "2020T2",
                    "isin": "ES0119483008",
                    "nombre": "ABANCA RENTA FIJA PATRIMONIO, FI CLASE A",
                    "porcentaje": 0.16
                },
                {
                    "cantidad": 0.0,
                    "desde": "2019T4",
                    "isin": "ES0126551003",
                    "nombre": "GESTIFONSA RENTA FIJA CORTO PLAZO, FI CLASE CARTERA",
                    "porcentaje": 0.0
                },
                {
                    "cantidad": 0.0,
                    "desde": "2019T4",
                    "isin": "ES0126551037",
                    "nombre": "GESTIFONSA RENTA FIJA CORTO PLAZO, FI CLASE BASE",
                    "porcentaje": 0.0
                }
            ],
            "periodo": "2020T2"
        },
        {
            "fondos": [
                {
                    "cantidad": 617884.0,
                    "desde": "2019T4",
                    "isin": "ES0126551003",
                    "nombre": "GESTIFONSA RENTA FIJA CORTO PLAZO, FI CLASE CARTERA",
                    "porcentaje": 0.96
                },
                {
                    "cantidad": 617884.0,
                    "desde": "2019T4",
                    "isin": "ES0126551037",
                    "nombre": "GESTIFONSA RENTA FIJA CORTO PLAZO, FI CLASE BASE",
                    "porcentaje": 0.96
                },
                {
                    "cantidad": 969790.0,
                    "desde": "2018T1",
                    "isin": "ES0138816006",
                    "nombre": "MEDIOLANUM FONDCUENTA, FI CLASE E",
                    "porcentaje": 0.93
                },
                {
                    "cantidad": 969790.0,
                    "desde": "2018T1",
                    "isin": "ES0138816030",
                    "nombre": "MEDIOLANUM FONDCUENTA, FI CLASE S",
                    "porcentaje": 0.93
                },
                {
                    "cantidad": 209922.0,
                    "desde": "2019T3",
                    "isin": "ES0137389005",
                    "nombre": "MEDIOLANUM CRECIMIENTO, FI CLASE L-A",
                    "porcentaje": 0.45
                },
                {
                    "cantidad": 209922.0,
                    "desde": "2019T3",
                    "isin": "ES0137389013",
                    "nombre": "MEDIOLANUM CRECIMIENTO, FI CLASE L-B",
                    "porcentaje": 0.45
                },
                {
                    "cantidad": 209922.0,
                    "desde": "2019T3",
                    "isin": "ES0137389021",
                    "nombre": "MEDIOLANUM CRECIMIENTO, FI CLASE S-B",
                    "porcentaje": 0.45
                },
                {
                    "cantidad": 209922.0,
                    "desde": "2019T3",
                    "isin": "ES0137389039",
                    "nombre": "MEDIOLANUM CRECIMIENTO, FI CLASE S-A",
                    "porcentaje": 0.45
                },
                {
                    "cantidad": 209922.0,
                    "desde": "2019T3",
                    "isin": "ES0137389047",
                    "nombre": "MEDIOLANUM CRECIMIENTO, FI CLASE E-A",
                    "porcentaje": 0.45
                },
                {
                    "cantidad": 209922.0,
                    "desde": "2019T3",
                    "isin": "ES0137389054",
                    "nombre": "MEDIOLANUM CRECIMIENTO, FI CLASE E-B",
                    "porcentaje": 0.45
                },
                {
                    "cantidad": 104866.0,
                    "desde": "2019T3",
                    "isin": "ES0180552004",
                    "nombre": "TREA CAJAMAR VALOR, FI",
                    "porcentaje": 0.35
                },
                {
                    "cantidad": 1863030.0,
                    "desde": "2017T3",
                    "isin": "ES0165127004",
                    "nombre": "MEDIOLANUM ACTIVO, FI CLASE L-A",
                    "porcentaje": 0.25
                },
                {
                    "cantidad": 1863030.0,
                    "desde": "2017T3",
                    "isin": "ES0165127012",
                    "nombre": "MEDIOLANUM ACTIVO, FI CLASE S-B",
                    "porcentaje": 0.25
                },
                {
                    "cantidad": 1863030.0,
                    "desde": "2017T3",
                    "isin": "ES0165127020",
                    "nombre": "MEDIOLANUM ACTIVO, FI CLASE L-B",
                    "porcentaje": 0.25
                },
                {
                    "cantidad": 1863030.0,
                    "desde": "2017T3",
                    "isin": "ES0165127038",
                    "nombre": "MEDIOLANUM ACTIVO, FI CLASE S-A",
                    "porcentaje": 0.25
                },
                {
                    "cantidad": 1863030.0,
                    "desde": "2017T3",
                    "isin": "ES0165127046",
                    "nombre": "MEDIOLANUM ACTIVO, FI CLASE E-A",
                    "porcentaje": 0.25
                },
                {
                    "cantidad": 1863030.0,
                    "desde": "2017T3",
                    "isin": "ES0165127053",
                    "nombre": "MEDIOLANUM ACTIVO, FI CLASE E-B",
                    "porcentaje": 0.25
                },
                {
                    "cantidad": 1038045.0,
                    "desde": "2019T4",
                    "isin": "ES0114546031",
                    "nombre": "TREA CAJAMAR CORTO PLAZO FI CLASE A",
                    "porcentaje": 0.19
                },
                {
                    "cantidad": 838916.0,
                    "desde": "2019T3",
                    "isin": "ES0114547039",
                    "nombre": "TREA CAJAMAR PATRIMONIO FI",
                    "porcentaje": 0.19
                },
                {
                    "cantidad": 209729.0,
                    "desde": "2019T3",
                    "isin": "ES0109226037",
                    "nombre": "TREA CAJAMAR CRECIMIENTO FI",
                    "porcentaje": 0.18
                }
            ],
            "periodo": "2020T1"
        },
        {
            "fondos": [
                {
                    "cantidad": 633990.0,
                    "desde": "2019T4",
                    "isin": "ES0126551003",
                    "nombre": "GESTIFONSA RENTA FIJA CORTO PLAZO, FI CLASE CARTERA",
                    "porcentaje": 0.93
                },
                {
                    "cantidad": 633990.0,
                    "desde": "2019T4",
                    "isin": "ES0126551037",
                    "nombre": "GESTIFONSA RENTA FIJA CORTO PLAZO, FI CLASE BASE",
                    "porcentaje": 0.93
                },
                {
                    "cantidad": 997241.0,
                    "desde": "2018T1",
                    "isin": "ES0138816006",
                    "nombre": "MEDIOLANUM FONDCUENTA, FI CLASE E",
                    "porcentaje": 0.91
                },
                {
                    "cantidad": 997241.0,
                    "desde": "2018T1",
                    "isin": "ES0138816030",
                    "nombre": "MEDIOLANUM FONDCUENTA, FI CLASE S",
                    "porcentaje": 0.91
                },
                {
                    "cantidad": 215396.0,
                    "desde": "2019T3",
                    "isin": "ES0137389005",
                    "nombre": "MEDIOLANUM CRECIMIENTO, FI CLASE L-A",
                    "porcentaje": 0.35
                },
                {
                    "cantidad": 215396.0,
                    "desde": "2019T3",
                    "isin": "ES0137389013",
                    "nombre": "MEDIOLANUM CRECIMIENTO, FI CLASE L-B",
                    "porcentaje": 0.35
                },
                {
                    "cantidad": 215396.0,
                    "desde": "2019T3",
                    "isin": "ES0137389021",
                    "nombre": "MEDIOLANUM CRECIMIENTO, FI CLASE S-B",
                    "porcentaje": 0.35
                },
                {
                    "cantidad": 215396.0,
                    "desde": "2019T3",
                    "isin": "ES0137389039",
                    "nombre": "MEDIOLANUM CRECIMIENTO, FI CLASE S-A",
                    "porcentaje": 0.35
                },
                {
                    "cantidad": 215396.0,
                    "desde": "2019T3",
                    "isin": "ES0137389047",
                    "nombre": "MEDIOLANUM CRECIMIENTO, FI CLASE E-A",
                    "porcentaje": 0.35
                },
                {
                    "cantidad": 215396.0,
                    "desde": "2019T3",
                    "isin": "ES0137389054",
                    "nombre": "MEDIOLANUM CRECIMIENTO, FI CLASE E-B",
                    "porcentaje": 0.35
                },
                {
                    "cantidad": 107342.0,
                    "desde": "2019T3",
                    "isin": "ES0180552004",
                    "nombre": "TREA CAJAMAR VALOR, FI",
                    "porcentaje": 0.3
                },
                {
                    "cantidad": 1913443.0,
                    "desde": "2017T3",
                    "isin": "ES0165127004",
                    "nombre": "MEDIOLANUM ACTIVO, FI CLASE L-A",
                    "porcentaje": 0.25
                },
                {
                    "cantidad": 1913443.0,
                    "desde": "2017T3",
                    "isin": "ES0165127012",
                    "nombre": "MEDIOLANUM ACTIVO, FI CLASE S-B",
                    "porcentaje": 0.25
                },
                {
                    "cantidad": 1913443.0,
                    "desde": "2017T3",
                    "isin": "ES0165127020",
                    "nombre": "MEDIOLANUM ACTIVO, FI CLASE L-B",
                    "porcentaje": 0.25
                },
                {
                    "cantidad": 1913443.0,
                    "desde": "2017T3",
                    "isin": "ES0165127038",
                    "nombre": "MEDIOLANUM ACTIVO, FI CLASE S-A",
                    "porcentaje": 0.25
                },
                {
                    "cantidad": 1913443.0,
                    "desde": "2017T3",
                    "isin": "ES0165127046",
                    "nombre": "MEDIOLANUM ACTIVO, FI CLASE E-A",
                    "porcentaje": 0.25
                },
                {
                    "cantidad": 1913443.0,
                    "desde": "2017T3",
                    "isin": "ES0165127053",
                    "nombre": "MEDIOLANUM ACTIVO, FI CLASE E-B",
                    "porcentaje": 0.25
                },
                {
                    "cantidad": 1062209.0,
                    "desde": "2019T4",
                    "isin": "ES0114546031",
                    "nombre": "TREA CAJAMAR CORTO PLAZO FI CLASE A",
                    "porcentaje": 0.2
                },
                {
                    "cantidad": 858727.0,
                    "desde": "2019T3",
                    "isin": "ES0114547039",
                    "nombre": "TREA CAJAMAR PATRIMONIO FI",
                    "porcentaje": 0.16
                },
                {
                    "cantidad": 214682.0,
                    "desde": "2019T3",
                    "isin": "ES0109226037",
                    "nombre": "TREA CAJAMAR CRECIMIENTO FI",
                    "porcentaje": 0.14
                }
            ],
            "periodo": "2019T4"
        },
        {
            "fondos": [
                {
                    "cantidad": 996155.0,
                    "desde": "2018T1",
                    "isin": "ES0138816006",
                    "nombre": "MEDIOLANUM FONDCUENTA, FI CLASE E",
                    "porcentaje": 0.93
                },
                {
                    "cantidad": 996155.0,
                    "desde": "2018T1",
                    "isin": "ES0138816030",
                    "nombre": "MEDIOLANUM FONDCUENTA, FI CLASE S",
                    "porcentaje": 0.93
                },
                {
                    "cantidad": 214518.0,
                    "desde": "2019T3",
                    "isin": "ES0137389005",
                    "nombre": "MEDIOLANUM CRECIMIENTO, FI CLASE L-A",
                    "porcentaje": 0.33
                },
                {
                    "cantidad": 214518.0,
                    "desde": "2019T3",
                    "isin": "ES0137389013",
                    "nombre": "MEDIOLANUM CRECIMIENTO, FI CLASE L-B",
                    "porcentaje": 0.33
                },
                {
                    "cantidad": 214518.0,
                    "desde": "2019T3",
                    "isin": "ES0137389021",
                    "nombre": "MEDIOLANUM CRECIMIENTO, FI CLASE S-B",
                    "porcentaje": 0.33
                },
                {
                    "cantidad": 214518.0,
                    "desde": "2019T3",
                    "isin": "ES0137389039",
                    "nombre": "MEDIOLANUM CRECIMIENTO, FI CLASE S-A",
                    "porcentaje": 0.33
                },
                {
                    "cantidad": 214518.0,
                    "desde": "2019T3",
                    "isin": "ES0137389047",
                    "nombre": "MEDIOLANUM CRECIMIENTO, FI CLASE E-A",
                    "porcentaje": 0.33
                },
                {
                    "cantidad": 214518.0,
                    "desde": "2019T3",
                    "isin": "ES0137389054",
                    "nombre": "MEDIOLANUM CRECIMIENTO, FI CLASE E-B",
                    "porcentaje": 0.33
                },
                {
                    "cantidad": 107054.0,
                    "desde": "2019T3",
                    "isin": "ES0180552004",
                    "nombre": "TREA CAJAMAR VALOR, FI",
                    "porcentaje": 0.3
                },
                {
                    "cantidad": 1908324.0,
                    "desde": "2017T3",
                    "isin": "ES0165127004",
                    "nombre": "MEDIOLANUM ACTIVO, FI CLASE L-A",
                    "porcentaje": 0.29
                },
                {
                    "cantidad": 1908324.0,
                    "desde": "2017T3",
                    "isin": "ES0165127012",
                    "nombre": "MEDIOLANUM ACTIVO, FI CLASE S-B",
                    "porcentaje": 0.29
                },
                {
                    "cantidad": 1908324.0,
                    "desde": "2017T3",
                    "isin": "ES0165127020",
                    "nombre": "MEDIOLANUM ACTIVO, FI CLASE L-B",
                    "porcentaje": 0.29
                },
                {
                    "cantidad": 1908324.0,
                    "desde": "2017T3",
                    "isin": "ES0165127038",
                    "nombre": "MEDIOLANUM ACTIVO, FI CLASE S-A",
                    "porcentaje": 0.29
                },
                {
                    "cantidad": 1908324.0,
                    "desde": "2017T3",
                    "isin": "ES0165127046",
                    "nombre": "MEDIOLANUM ACTIVO, FI CLASE E-A",
                    "porcentaje": 0.29
                },
                {
                    "cantidad": 1908324.0,
                    "desde": "2017T3",
                    "isin": "ES0165127053",
                    "nombre": "MEDIOLANUM ACTIVO, FI CLASE E-B",
                    "porcentaje": 0.29
                },
                {
                    "cantidad": 856436.0,
                    "desde": "2019T3",
                    "isin": "ES0114547039",
                    "nombre": "TREA CAJAMAR PATRIMONIO FI",
                    "porcentaje": 0.16
                },
                {
                    "cantidad": 214109.0,
                    "desde": "2019T3",
                    "isin": "ES0109226037",
                    "nombre": "TREA CAJAMAR CRECIMIENTO FI",
                    "porcentaje": 0.14
                }
            ],
            "periodo": "2019T3"
        },
        {
            "fondos": [
                {
                    "cantidad": 991205.0,
                    "desde": "2018T1",
                    "isin": "ES0138816006",
                    "nombre": "MEDIOLANUM FONDCUENTA, FI CLASE E",
                    "porcentaje": 0.92
                },
                {
                    "cantidad": 991205.0,
                    "desde": "2018T1",
                    "isin": "ES0138816030",
                    "nombre": "MEDIOLANUM FONDCUENTA, FI CLASE S",
                    "porcentaje": 0.92
                },
                {
                    "cantidad": 561205.0,
                    "desde": "2017T3",
                    "isin": "ES0165127004",
                    "nombre": "MEDIOLANUM ACTIVO, FI CLASE L-A",
                    "porcentaje": 0.09
                },
                {
                    "cantidad": 561205.0,
                    "desde": "2017T3",
                    "isin": "ES0165127012",
                    "nombre": "MEDIOLANUM ACTIVO, FI CLASE S-B",
                    "porcentaje": 0.09
                },
                {
                    "cantidad": 561205.0,
                    "desde": "2017T3",
                    "isin": "ES0165127020",
                    "nombre": "MEDIOLANUM ACTIVO, FI CLASE L-B",
                    "porcentaje": 0.09
                },
                {
                    "cantidad": 561205.0,
                    "desde": "2017T3",
                    "isin": "ES0165127038",
                    "nombre": "MEDIOLANUM ACTIVO, FI CLASE S-A",
                    "porcentaje": 0.09
                },
                {
                    "cantidad": 561205.0,
                    "desde": "2017T3",
                    "isin": "ES0165127046",
                    "nombre": "MEDIOLANUM ACTIVO, FI CLASE E-A",
                    "porcentaje": 0.09
                },
                {
                    "cantidad": 561205.0,
                    "desde": "2017T3",
                    "isin": "ES0165127053",
                    "nombre": "MEDIOLANUM ACTIVO, FI CLASE E-B",
                    "porcentaje": 0.09
                }
            ],
            "periodo": "2019T2"
        },
        {
            "fondos": [
                {
                    "cantidad": 974507.0,
                    "desde": "2018T1",
                    "isin": "ES0138816006",
                    "nombre": "MEDIOLANUM FONDCUENTA, FI CLASE E",
                    "porcentaje": 1.93
                },
                {
                    "cantidad": 974507.0,
                    "desde": "2018T1",
                    "isin": "ES0138816030",
                    "nombre": "MEDIOLANUM FONDCUENTA, FI CLASE S",
                    "porcentaje": 1.93
                },
                {
                    "cantidad": 552173.0,
                    "desde": "2017T3",
                    "isin": "ES0165127004",
                    "nombre": "MEDIOLANUM ACTIVO, FI CLASE L-A",
                    "porcentaje": 0.1
                },
                {
                    "cantidad": 552173.0,
                    "desde": "2017T3",
                    "isin": "ES0165127012",
                    "nombre": "MEDIOLANUM ACTIVO, FI CLASE S-B",
                    "porcentaje": 0.1
                },
                {
                    "cantidad": 552173.0,
                    "desde": "2017T3",
                    "isin": "ES0165127020",
                    "nombre": "MEDIOLANUM ACTIVO, FI CLASE L-B",
                    "porcentaje": 0.1
                },
                {
                    "cantidad": 552173.0,
                    "desde": "2017T3",
                    "isin": "ES0165127038",
                    "nombre": "MEDIOLANUM ACTIVO, FI CLASE S-A",
                    "porcentaje": 0.1
                },
                {
                    "cantidad": 552173.0,
                    "desde": "2017T3",
                    "isin": "ES0165127046",
                    "nombre": "MEDIOLANUM ACTIVO, FI CLASE E-A",
                    "porcentaje": 0.1
                },
                {
                    "cantidad": 552173.0,
                    "desde": "2017T3",
                    "isin": "ES0165127053",
                    "nombre": "MEDIOLANUM ACTIVO, FI CLASE E-B",
                    "porcentaje": 0.1
                }
            ],
            "periodo": "2019T1"
        },
        {
            "fondos": [
                {
                    "cantidad": 745093.0,
                    "desde": "2018T1",
                    "isin": "ES0138816006",
                    "nombre": "MEDIOLANUM FONDCUENTA, FI CLASE E",
                    "porcentaje": 1.51
                },
                {
                    "cantidad": 745093.0,
                    "desde": "2018T1",
                    "isin": "ES0138816030",
                    "nombre": "MEDIOLANUM FONDCUENTA, FI CLASE S",
                    "porcentaje": 1.51
                },
                {
                    "cantidad": 540022.0,
                    "desde": "2017T3",
                    "isin": "ES0165127004",
                    "nombre": "MEDIOLANUM ACTIVO, FI CLASE L-A",
                    "porcentaje": 0.1
                },
                {
                    "cantidad": 540022.0,
                    "desde": "2017T3",
                    "isin": "ES0165127012",
                    "nombre": "MEDIOLANUM ACTIVO, FI CLASE S-B",
                    "porcentaje": 0.1
                },
                {
                    "cantidad": 540022.0,
                    "desde": "2017T3",
                    "isin": "ES0165127020",
                    "nombre": "MEDIOLANUM ACTIVO, FI CLASE L-B",
                    "porcentaje": 0.1
                },
                {
                    "cantidad": 540022.0,
                    "desde": "2017T3",
                    "isin": "ES0165127038",
                    "nombre": "MEDIOLANUM ACTIVO, FI CLASE S-A",
                    "porcentaje": 0.1
                },
                {
                    "cantidad": 540022.0,
                    "desde": "2017T3",
                    "isin": "ES0165127046",
                    "nombre": "MEDIOLANUM ACTIVO, FI CLASE E-A",
                    "porcentaje": 0.1
                },
                {
                    "cantidad": 540022.0,
                    "desde": "2017T3",
                    "isin": "ES0165127053",
                    "nombre": "MEDIOLANUM ACTIVO, FI CLASE E-B",
                    "porcentaje": 0.1
                },
                {
                    "cantidad": 269674.0,
                    "desde": "2017T4",
                    "isin": "ES0114546031",
                    "nombre": "TREA CAJAMAR CORTO PLAZO FI CLASE A",
                    "porcentaje": 0.07
                }
            ],
            "periodo": "2018T4"
        },
        {
            "fondos": [
                {
                    "cantidad": 754573.0,
                    "desde": "2018T1",
                    "isin": "ES0138816006",
                    "nombre": "MEDIOLANUM FONDCUENTA, FI CLASE E",
                    "porcentaje": 1.51
                },
                {
                    "cantidad": 754573.0,
                    "desde": "2018T1",
                    "isin": "ES0138816030",
                    "nombre": "MEDIOLANUM FONDCUENTA, FI CLASE S",
                    "porcentaje": 1.51
                },
                {
                    "cantidad": 547096.0,
                    "desde": "2017T3",
                    "isin": "ES0165127004",
                    "nombre": "MEDIOLANUM ACTIVO, FI CLASE L-A",
                    "porcentaje": 0.1
                },
                {
                    "cantidad": 547096.0,
                    "desde": "2017T3",
                    "isin": "ES0165127012",
                    "nombre": "MEDIOLANUM ACTIVO, FI CLASE S-B",
                    "porcentaje": 0.1
                },
                {
                    "cantidad": 547096.0,
                    "desde": "2017T3",
                    "isin": "ES0165127020",
                    "nombre": "MEDIOLANUM ACTIVO, FI CLASE L-B",
                    "porcentaje": 0.1
                },
                {
                    "cantidad": 547096.0,
                    "desde": "2017T3",
                    "isin": "ES0165127038",
                    "nombre": "MEDIOLANUM ACTIVO, FI CLASE S-A",
                    "porcentaje": 0.1
                },
                {
                    "cantidad": 547096.0,
                    "desde": "2017T3",
                    "isin": "ES0165127046",
                    "nombre": "MEDIOLANUM ACTIVO, FI CLASE E-A",
                    "porcentaje": 0.1
                },
                {
                    "cantidad": 547096.0,
                    "desde": "2017T3",
                    "isin": "ES0165127053",
                    "nombre": "MEDIOLANUM ACTIVO, FI CLASE E-B",
                    "porcentaje": 0.1
                },
                {
                    "cantidad": 272046.0,
                    "desde": "2017T4",
                    "isin": "ES0114546031",
                    "nombre": "TREA CAJAMAR CORTO PLAZO FI CLASE A",
                    "porcentaje": 0.07
                }
            ],
            "periodo": "2018T3"
        },
        {
            "fondos": [
                {
                    "cantidad": 752896.0,
                    "desde": "2018T1",
                    "isin": "ES0138816006",
                    "nombre": "MEDIOLANUM FONDCUENTA, FI CLASE E",
                    "porcentaje": 1.47
                },
                {
                    "cantidad": 752896.0,
                    "desde": "2018T1",
                    "isin": "ES0138816030",
                    "nombre": "MEDIOLANUM FONDCUENTA, FI CLASE S",
                    "porcentaje": 1.47
                },
                {
                    "cantidad": 546200.0,
                    "desde": "2017T3",
                    "isin": "ES0165127004",
                    "nombre": "MEDIOLANUM ACTIVO, FI CLASE L-A",
                    "porcentaje": 0.1
                },
                {
                    "cantidad": 546200.0,
                    "desde": "2017T3",
                    "isin": "ES0165127012",
                    "nombre": "MEDIOLANUM ACTIVO, FI CLASE S-B",
                    "porcentaje": 0.1
                },
                {
                    "cantidad": 546200.0,
                    "desde": "2017T3",
                    "isin": "ES0165127020",
                    "nombre": "MEDIOLANUM ACTIVO, FI CLASE L-B",
                    "porcentaje": 0.1
                },
                {
                    "cantidad": 546200.0,
                    "desde": "2017T3",
                    "isin": "ES0165127038",
                    "nombre": "MEDIOLANUM ACTIVO, FI CLASE S-A",
                    "porcentaje": 0.1
                },
                {
                    "cantidad": 546200.0,
                    "desde": "2017T3",
                    "isin": "ES0165127046",
                    "nombre": "MEDIOLANUM ACTIVO, FI CLASE E-A",
                    "porcentaje": 0.1
                },
                {
                    "cantidad": 546200.0,
                    "desde": "2017T3",
                    "isin": "ES0165127053",
                    "nombre": "MEDIOLANUM ACTIVO, FI CLASE E-B",
                    "porcentaje": 0.1
                },
                {
                    "cantidad": 271522.0,
                    "desde": "2017T4",
                    "isin": "ES0114546031",
                    "nombre": "TREA CAJAMAR CORTO PLAZO FI CLASE A",
                    "porcentaje": 0.07
                }
            ],
            "periodo": "2018T2"
        },
        {
            "fondos": [
                {
                    "cantidad": 544911.0,
                    "desde": "2018T1",
                    "isin": "ES0138816006",
                    "nombre": "MEDIOLANUM FONDCUENTA, FI CLASE E",
                    "porcentaje": 1.04
                },
                {
                    "cantidad": 544911.0,
                    "desde": "2018T1",
                    "isin": "ES0138816030",
                    "nombre": "MEDIOLANUM FONDCUENTA, FI CLASE S",
                    "porcentaje": 1.04
                },
                {
                    "cantidad": 553143.0,
                    "desde": "2017T3",
                    "isin": "ES0165127004",
                    "nombre": "MEDIOLANUM ACTIVO, FI CLASE L-A",
                    "porcentaje": 0.11
                },
                {
                    "cantidad": 553143.0,
                    "desde": "2017T3",
                    "isin": "ES0165127012",
                    "nombre": "MEDIOLANUM ACTIVO, FI CLASE S-B",
                    "porcentaje": 0.11
                },
                {
                    "cantidad": 553143.0,
                    "desde": "2017T3",
                    "isin": "ES0165127020",
                    "nombre": "MEDIOLANUM ACTIVO, FI CLASE L-B",
                    "porcentaje": 0.11
                },
                {
                    "cantidad": 553143.0,
                    "desde": "2017T3",
                    "isin": "ES0165127038",
                    "nombre": "MEDIOLANUM ACTIVO, FI CLASE S-A",
                    "porcentaje": 0.11
                },
                {
                    "cantidad": 553143.0,
                    "desde": "2017T3",
                    "isin": "ES0165127046",
                    "nombre": "MEDIOLANUM ACTIVO, FI CLASE E-A",
                    "porcentaje": 0.11
                },
                {
                    "cantidad": 553143.0,
                    "desde": "2017T3",
                    "isin": "ES0165127053",
                    "nombre": "MEDIOLANUM ACTIVO, FI CLASE E-B",
                    "porcentaje": 0.11
                },
                {
                    "cantidad": 274957.0,
                    "desde": "2017T4",
                    "isin": "ES0114546031",
                    "nombre": "TREA CAJAMAR CORTO PLAZO FI CLASE A",
                    "porcentaje": 0.08
                }
            ],
            "periodo": "2018T1"
        },
        {
            "fondos": [
                {
                    "cantidad": 552326.0,
                    "desde": "2017T3",
                    "isin": "ES0165127004",
                    "nombre": "MEDIOLANUM ACTIVO, FI CLASE L-A",
                    "porcentaje": 0.13
                },
                {
                    "cantidad": 552326.0,
                    "desde": "2017T3",
                    "isin": "ES0165127012",
                    "nombre": "MEDIOLANUM ACTIVO, FI CLASE S-B",
                    "porcentaje": 0.13
                },
                {
                    "cantidad": 552326.0,
                    "desde": "2017T3",
                    "isin": "ES0165127020",
                    "nombre": "MEDIOLANUM ACTIVO, FI CLASE L-B",
                    "porcentaje": 0.13
                },
                {
                    "cantidad": 552326.0,
                    "desde": "2017T3",
                    "isin": "ES0165127038",
                    "nombre": "MEDIOLANUM ACTIVO, FI CLASE S-A",
                    "porcentaje": 0.13
                },
                {
                    "cantidad": 552326.0,
                    "desde": "2017T3",
                    "isin": "ES0165127046",
                    "nombre": "MEDIOLANUM ACTIVO, FI CLASE E-A",
                    "porcentaje": 0.13
                },
                {
                    "cantidad": 552326.0,
                    "desde": "2017T3",
                    "isin": "ES0165127053",
                    "nombre": "MEDIOLANUM ACTIVO, FI CLASE E-B",
                    "porcentaje": 0.13
                },
                {
                    "cantidad": 275147.0,
                    "desde": "2017T4",
                    "isin": "ES0114546031",
                    "nombre": "TREA CAJAMAR CORTO PLAZO FI CLASE A",
                    "porcentaje": 0.07
                }
            ],
            "periodo": "2017T4"
        },
        {
            "fondos": [
                {
                    "cantidad": 551539.0,
                    "desde": "2017T3",
                    "isin": "ES0165127004",
                    "nombre": "MEDIOLANUM ACTIVO, FI CLASE L-A",
                    "porcentaje": 0.17
                },
                {
                    "cantidad": 551539.0,
                    "desde": "2017T3",
                    "isin": "ES0165127012",
                    "nombre": "MEDIOLANUM ACTIVO, FI CLASE S-B",
                    "porcentaje": 0.17
                },
                {
                    "cantidad": 551539.0,
                    "desde": "2017T3",
                    "isin": "ES0165127020",
                    "nombre": "MEDIOLANUM ACTIVO, FI CLASE L-B",
                    "porcentaje": 0.17
                },
                {
                    "cantidad": 551539.0,
                    "desde": "2017T3",
                    "isin": "ES0165127038",
                    "nombre": "MEDIOLANUM ACTIVO, FI CLASE S-A",
                    "porcentaje": 0.17
                },
                {
                    "cantidad": 551539.0,
                    "desde": "2017T3",
                    "isin": "ES0165127046",
                    "nombre": "MEDIOLANUM ACTIVO, FI CLASE E-A",
                    "porcentaje": 0.17
                },
                {
                    "cantidad": 551539.0,
                    "desde": "2017T3",
                    "isin": "ES0165127053",
                    "nombre": "MEDIOLANUM ACTIVO, FI CLASE E-B",
                    "porcentaje": 0.17
                }
            ],
            "periodo": "2017T3"
        },
        {
            "fondos": [
                {
                    "cantidad": 2178470.0,
                    "desde": "2015T2",
                    "isin": "ES0138841038",
                    "nombre": "FONMARCH, FI CLASE A",
                    "porcentaje": 1.35
                }
            ],
            "periodo": "2016T2"
        },
        {
            "fondos": [
                {
                    "cantidad": 2181884.0,
                    "desde": "2015T2",
                    "isin": "ES0138841038",
                    "nombre": "FONMARCH, FI CLASE A",
                    "porcentaje": 1.29
                }
            ],
            "periodo": "2016T1"
        },
        {
            "fondos": [
                {
                    "cantidad": 2132250.0,
                    "desde": "2015T2",
                    "isin": "ES0138841038",
                    "nombre": "FONMARCH, FI CLASE A",
                    "porcentaje": 0.98
                }
            ],
            "periodo": "2015T4"
        },
        {
            "fondos": [
                {
                    "cantidad": 2048422.0,
                    "desde": "2015T2",
                    "isin": "ES0138841038",
                    "nombre": "FONMARCH, FI CLASE A",
                    "porcentaje": 0.87
                }
            ],
            "periodo": "2015T3"
        },
        {
            "fondos": [
                {
                    "cantidad": 2020529.0,
                    "desde": "2015T2",
                    "isin": "ES0138841038",
                    "nombre": "FONMARCH, FI CLASE A",
                    "porcentaje": 0.79
                }
            ],
            "periodo": "2015T2"
        }
    ],
    "isin": "IT0004720436",
    "nombre": "BONO|MEDIOBANCA SPA|4,50|2021-06-13"
}