{
    "historico_periodos": [
        {
            "fondos": [
                {
                    "cantidad": 93784.0,
                    "desde": "2023T2",
                    "isin": "ES0164701023",
                    "nombre": "MULTIADVISOR GESTION CFG 1855 RENTA FIJA MIXTA INTERNACIONAL",
                    "porcentaje": 4.32
                }
            ],
            "periodo": "2023T4"
        },
        {
            "fondos": [
                {
                    "cantidad": 90568.0,
                    "desde": "2023T2",
                    "isin": "ES0164701023",
                    "nombre": "MULTIADVISOR GESTION CFG 1855 RENTA FIJA MIXTA INTERNACIONAL",
                    "porcentaje": 4.36
                }
            ],
            "periodo": "2023T2"
        }
    ],
    "isin": "XS2294854745",
    "nombre": "BONO|GOLDSTORY SAS|5,38|2026-03-01"
}